certbot_aws_store/__init__.py
certbot_aws_store/acme_config.py
certbot_aws_store/acme_store.py
certbot_aws_store/backends.py
certbot_aws_store/certbot_wrappers.py
certbot_aws_store/certificate.py
certbot_aws_store/cli.py
certbot_aws_store/cron_function.py
certbot_aws_store/registry.py
certbot_aws_store/utils.py
certbot_aws_store-0.4.2.post0.dist-info/LICENSE
certbot_aws_store-0.4.2.post0.dist-info/METADATA
certbot_aws_store-0.4.2.post0.dist-info/WHEEL
certbot_aws_store-0.4.2.post0.dist-info/entry_points.txt
certbot_aws_store-0.4.2.post0.dist-info/RECORD
