Metadata-Version: 2.1
Name: certbot-aws-store
Version: 0.4.2.post0
Summary: Generate Let's Encrypt certificates and store into AWS
Keywords: compose-x,aws,certbot,ACME
Author: John Preston
Author-email: john@ews-network.net
Maintainer: John Preston
Maintainer-email: john@ews-network.net
Requires-Python: >=3.8,<4.0
Classifier: Development Status :: 4 - Beta
Classifier: Intended Audience :: Developers
Classifier: Intended Audience :: Information Technology
Classifier: Intended Audience :: System Administrators
Classifier: License :: OSI Approved :: Mozilla Public License 2.0 (MPL 2.0)
Classifier: Natural Language :: English
Classifier: Programming Language :: Python :: 3
Classifier: Programming Language :: Python :: 3.8
Classifier: Programming Language :: Python :: 3.9
Classifier: Programming Language :: Python :: 3.10
Classifier: Programming Language :: Python :: 3.11
Classifier: Programming Language :: Python :: 3
Classifier: Programming Language :: Python :: 3.10
Classifier: Programming Language :: Python :: 3.8
Classifier: Programming Language :: Python :: 3.9
Provides-Extra: certbot
Provides-Extra: cli
Requires-Dist: argparse (>=1.4.0,<2.0.0)
Requires-Dist: b-dynamodb-common (>=0.4.1,<0.5.0)
Requires-Dist: certbot (>=2.3.0,<3.0.0) ; extra == "cli" or extra == "certbot"
Requires-Dist: certbot-dns-route53 (>=2.3,<3.0) ; extra == "cli" or extra == "certbot"
Requires-Dist: compose-x-common (>=1.2,<2.0)
Requires-Dist: pyOpenSSL (>=22.0.0,<23.0.0)
Requires-Dist: pynamodb (>=5.2.1,<6.0.0)
